sqlite3_zlib_adapter/__init__.py
sqlite3_zlib_adapter-0.1.0.dist-info/DESCRIPTION.rst
sqlite3_zlib_adapter-0.1.0.dist-info/METADATA
sqlite3_zlib_adapter-0.1.0.dist-info/RECORD
sqlite3_zlib_adapter-0.1.0.dist-info/WHEEL
sqlite3_zlib_adapter-0.1.0.dist-info/metadata.json
sqlite3_zlib_adapter-0.1.0.dist-info/top_level.txt
