Metadata-Version: 2.0
Name: sqlite3-zlib-adapter
Version: 0.1.0
Summary: sqlite3_zlip_adapter is a custom class with adapter and convert function to store strings into a SQLite column as zlib blobs.
Home-page: https://github.com/migonzalvar/sqlite3_zlib_adapter
Author: Miguel González
Author-email: migonzalvar@gmail.com
License: Apache Software License 2.0
Keywords: sqlite3_zlib_adapter
Platform: UNKNOWN
Classifier: Development Status :: 2 - Pre-Alpha
Classifier: Intended Audience :: Developers
Classifier: License :: OSI Approved :: Apache Software License
Classifier: Natural Language :: English
Classifier: Programming Language :: Python :: 3
Classifier: Programming Language :: Python :: 3.5
Classifier: Programming Language :: Python :: 3.6
